{
	"animations": [
		{
			"loop": false,
			"offsets": [
				-14,
				-5
			],
			"anim": "singRIGHTmiss",
			"fps": 24,
			"name": "MISS RIGHT",
			"indices": []
		},
		{
			"loop": false,
			"offsets": [
				7,
				-2
			],
			"anim": "singLEFTmiss",
			"fps": 24,
			"name": "MISS LEFT",
			"indices": []
		},
		{
			"loop": false,
			"offsets": [
				-13,
				4
			],
			"anim": "singUPmiss",
			"fps": 24,
			"name": "MISS UP",
			"indices": []
		},
		{
			"loop": false,
			"offsets": [
				-4,
				-11
			],
			"anim": "singDOWNmiss",
			"fps": 24,
			"name": "MISS DOWN",
			"indices": []
		},
		{
			"offsets": [
				0,
				0
			],
			"loop": true,
			"fps": 24,
			"anim": "firstDeath",
			"indices": [],
			"name": "MISS UP"
		},
		{
			"offsets": [
				0,
				0
			],
			"loop": true,
			"fps": 24,
			"anim": "deathLoop",
			"indices": [],
			"name": "MISS UP"
		},
		{
			"offsets": [
				0,
				0
			],
			"loop": true,
			"fps": 24,
			"anim": "deathConfirm",
			"indices": [],
			"name": "MISS UP"
		},
		{
			"loop": false,
			"offsets": [
				79,
				6
			],
			"anim": "singUP",
			"fps": 24,
			"name": "up",
			"indices": []
		},
		{
			"loop": false,
			"offsets": [
				89,
				-7
			],
			"anim": "singDOWN",
			"fps": 24,
			"name": "down",
			"indices": []
		},
		{
			"loop": false,
			"offsets": [
				89,
				1
			],
			"anim": "idle",
			"fps": 24,
			"name": "idle",
			"indices": []
		},
		{
			"loop": false,
			"offsets": [
				63,
				-1
			],
			"anim": "singRIGHT",
			"fps": 24,
			"name": "right",
			"indices": []
		},
		{
			"loop": false,
			"offsets": [
				107,
				2
			],
			"anim": "singLEFT",
			"fps": 24,
			"name": "left",
			"indices": []
		},
		{
			"offsets": [
				220,
				34
			],
			"loop": false,
			"fps": 24,
			"anim": "appears",
			"indices": [],
			"name": "appears"
		}
	],
	"vocals_file": "",
	"no_antialiasing": false,
	"image": "characters/kisserv2",
	"position": [
		20,
		190
	],
	"healthicon": "kisser",
	"flip_x": false,
	"healthbar_colors": [
		252,
		252,
		252
	],
	"camera_position": [
		-580,
		-60
	],
	"sing_duration": 6.1,
	"scale": 1.1,
	"_editor_isPlayer": false
}