<?xml version="1.0" encoding="utf-8"?>
<TextureAtlas imagePath="reggie boys.png">
	<!-- Created with Adobe Animate version 23.0.1.70 -->
	<!-- http://www.adobe.com/products/animate.html -->
	<SubTexture name="hi0000" x="0" y="0" width="371" height="705" frameX="-8" frameY="-2" frameWidth="398" frameHeight="707"/>
	<SubTexture name="hi0001" x="0" y="0" width="371" height="705" frameX="-8" frameY="-2" frameWidth="398" frameHeight="707"/>
	<SubTexture name="hi0002" x="371" y="0" width="385" height="691" frameX="-5" frameY="-16" frameWidth="398" frameHeight="707"/>
	<SubTexture name="hi0003" x="756" y="0" width="385" height="691" frameX="-5" frameY="-16" frameWidth="398" frameHeight="707"/>
	<SubTexture name="hi0004" x="1141" y="0" width="390" height="698" frameX="-6" frameY="-9" frameWidth="398" frameHeight="707"/>
	<SubTexture name="hi0005" x="1531" y="0" width="390" height="698" frameX="-6" frameY="-9" frameWidth="398" frameHeight="707"/>
	<SubTexture name="hi0006" x="1921" y="0" width="385" height="698" frameX="-6" frameY="-9" frameWidth="398" frameHeight="707"/>
	<SubTexture name="hi0007" x="2306" y="0" width="385" height="698" frameX="-6" frameY="-9" frameWidth="398" frameHeight="707"/>
	<SubTexture name="hi0008" x="2691" y="0" width="385" height="698" frameX="-6" frameY="-9" frameWidth="398" frameHeight="707"/>
	<SubTexture name="hi0009" x="2691" y="0" width="385" height="698" frameX="-6" frameY="-9" frameWidth="398" frameHeight="707"/>
	<SubTexture name="hi0010" x="2691" y="0" width="385" height="698" frameX="-6" frameY="-9" frameWidth="398" frameHeight="707"/>
	<SubTexture name="hi0011" x="2691" y="0" width="385" height="698" frameX="-6" frameY="-9" frameWidth="398" frameHeight="707"/>
	<SubTexture name="hi0012" x="2306" y="0" width="385" height="698" frameX="-6" frameY="-9" frameWidth="398" frameHeight="707"/>
	<SubTexture name="hi0013" x="2306" y="0" width="385" height="698" frameX="-6" frameY="-9" frameWidth="398" frameHeight="707"/>
	<SubTexture name="hi0014" x="2691" y="0" width="385" height="698" frameX="-6" frameY="-9" frameWidth="398" frameHeight="707"/>
	<SubTexture name="hi0015" x="2691" y="0" width="385" height="698" frameX="-6" frameY="-9" frameWidth="398" frameHeight="707"/>
	<SubTexture name="hi0016" x="2691" y="0" width="385" height="698" frameX="-6" frameY="-9" frameWidth="398" frameHeight="707"/>
	<SubTexture name="hi0017" x="3076" y="0" width="392" height="698" frameX="-6" frameY="-9" frameWidth="398" frameHeight="707"/>
	<SubTexture name="hi0018" x="3468" y="0" width="392" height="698" frameX="-6" frameY="-9" frameWidth="398" frameHeight="707"/>
	<SubTexture name="hi0019" x="3860" y="0" width="346" height="692" frameX="-3" frameY="-15" frameWidth="398" frameHeight="707"/>
	<SubTexture name="hi0020" x="4206" y="0" width="346" height="692" frameX="-3" frameY="-15" frameWidth="398" frameHeight="707"/>
	<SubTexture name="hi0021" x="4552" y="0" width="302" height="702" frameX="-6" frameY="-5" frameWidth="398" frameHeight="707"/>
	<SubTexture name="hi0022" x="4552" y="0" width="302" height="702" frameX="-6" frameY="-5" frameWidth="398" frameHeight="707"/>
	<SubTexture name="hi0023" x="4854" y="0" width="304" height="695" frameX="-4" frameY="-12" frameWidth="398" frameHeight="707"/>
	<SubTexture name="hi0024" x="5158" y="0" width="305" height="695" frameX="-4" frameY="-12" frameWidth="398" frameHeight="707"/>
	<SubTexture name="hi0025" x="5463" y="0" width="305" height="695" frameX="-4" frameY="-12" frameWidth="398" frameHeight="707"/>
	<SubTexture name="hi0026" x="5768" y="0" width="305" height="695" frameX="-4" frameY="-12" frameWidth="398" frameHeight="707"/>
	<SubTexture name="hi0027" x="6073" y="0" width="305" height="695" frameX="-4" frameY="-12" frameWidth="398" frameHeight="707"/>
	<SubTexture name="hi0028" x="6073" y="0" width="305" height="695" frameX="-4" frameY="-12" frameWidth="398" frameHeight="707"/>
	<SubTexture name="hi0029" x="6378" y="0" width="305" height="695" frameX="-4" frameY="-12" frameWidth="398" frameHeight="707"/>
	<SubTexture name="hi0030" x="6683" y="0" width="305" height="695" frameX="-4" frameY="-12" frameWidth="398" frameHeight="707"/>
	<SubTexture name="hi0031" x="5158" y="0" width="305" height="695" frameX="-4" frameY="-12" frameWidth="398" frameHeight="707"/>
	<SubTexture name="hi0032" x="6988" y="0" width="305" height="695" frameX="-4" frameY="-12" frameWidth="398" frameHeight="707"/>
	<SubTexture name="hi0033" x="7293" y="0" width="305" height="695" frameX="-4" frameY="-12" frameWidth="398" frameHeight="707"/>
	<SubTexture name="hi0034" x="7293" y="0" width="305" height="695" frameX="-4" frameY="-12" frameWidth="398" frameHeight="707"/>
	<SubTexture name="hi0035" x="7598" y="0" width="305" height="695" frameX="-4" frameY="-12" frameWidth="398" frameHeight="707"/>
	<SubTexture name="hi0036" x="0" y="705" width="305" height="695" frameX="-4" frameY="-12" frameWidth="398" frameHeight="707"/>
	<SubTexture name="hi0037" x="0" y="705" width="305" height="695" frameX="-4" frameY="-12" frameWidth="398" frameHeight="707"/>
	<SubTexture name="hi0038" x="7598" y="0" width="305" height="695" frameX="-4" frameY="-12" frameWidth="398" frameHeight="707"/>
	<SubTexture name="hi0039" x="7598" y="0" width="305" height="695" frameX="-4" frameY="-12" frameWidth="398" frameHeight="707"/>
	<SubTexture name="hi0040" x="7598" y="0" width="305" height="695" frameX="-4" frameY="-12" frameWidth="398" frameHeight="707"/>
	<SubTexture name="hi0041" x="7598" y="0" width="305" height="695" frameX="-4" frameY="-12" frameWidth="398" frameHeight="707"/>
	<SubTexture name="hi0042" x="0" y="705" width="305" height="695" frameX="-4" frameY="-12" frameWidth="398" frameHeight="707"/>
	<SubTexture name="hi0043" x="0" y="705" width="305" height="695" frameX="-4" frameY="-12" frameWidth="398" frameHeight="707"/>
	<SubTexture name="hi0044" x="7598" y="0" width="305" height="695" frameX="-4" frameY="-12" frameWidth="398" frameHeight="707"/>
	<SubTexture name="hi0045" x="7598" y="0" width="305" height="695" frameX="-4" frameY="-12" frameWidth="398" frameHeight="707"/>
	<SubTexture name="hi0046" x="7598" y="0" width="305" height="695" frameX="-4" frameY="-12" frameWidth="398" frameHeight="707"/>
	<SubTexture name="hi0047" x="7598" y="0" width="305" height="695" frameX="-4" frameY="-12" frameWidth="398" frameHeight="707"/>
	<SubTexture name="hi0048" x="0" y="705" width="305" height="695" frameX="-4" frameY="-12" frameWidth="398" frameHeight="707"/>
	<SubTexture name="hi0049" x="0" y="705" width="305" height="695" frameX="-4" frameY="-12" frameWidth="398" frameHeight="707"/>
	<SubTexture name="hi0050" x="7598" y="0" width="305" height="695" frameX="-4" frameY="-12" frameWidth="398" frameHeight="707"/>
	<SubTexture name="hi0051" x="7598" y="0" width="305" height="695" frameX="-4" frameY="-12" frameWidth="398" frameHeight="707"/>
	<SubTexture name="hi0052" x="7598" y="0" width="305" height="695" frameX="-4" frameY="-12" frameWidth="398" frameHeight="707"/>
	<SubTexture name="hi0053" x="7598" y="0" width="305" height="695" frameX="-4" frameY="-12" frameWidth="398" frameHeight="707"/>
	<SubTexture name="hi0054" x="0" y="705" width="305" height="695" frameX="-4" frameY="-12" frameWidth="398" frameHeight="707"/>
	<SubTexture name="hi0055" x="0" y="705" width="305" height="695" frameX="-4" frameY="-12" frameWidth="398" frameHeight="707"/>
	<SubTexture name="hi0056" x="7598" y="0" width="305" height="695" frameX="-4" frameY="-12" frameWidth="398" frameHeight="707"/>
	<SubTexture name="hi0057" x="305" y="705" width="305" height="695" frameX="-4" frameY="-12" frameWidth="398" frameHeight="707"/>
	<SubTexture name="hi0058" x="610" y="705" width="302" height="695" frameX="-4" frameY="-12" frameWidth="398" frameHeight="707"/>
	<SubTexture name="hi0059" x="912" y="705" width="302" height="695" frameX="-4" frameY="-12" frameWidth="398" frameHeight="707"/>
	<SubTexture name="hi0060" x="1214" y="705" width="317" height="695" frameX="-4" frameY="-12" frameWidth="398" frameHeight="707"/>
	<SubTexture name="hi0061" x="1531" y="705" width="318" height="695" frameX="-4" frameY="-12" frameWidth="398" frameHeight="707"/>
	<SubTexture name="hi0062" x="1849" y="705" width="316" height="695" frameX="-4" frameY="-12" frameWidth="398" frameHeight="707"/>
	<SubTexture name="hi0063" x="2165" y="705" width="316" height="695" frameX="-4" frameY="-12" frameWidth="398" frameHeight="707"/>
	<SubTexture name="hi0064" x="2165" y="705" width="316" height="695" frameX="-4" frameY="-12" frameWidth="398" frameHeight="707"/>
	<SubTexture name="hi0065" x="2481" y="705" width="316" height="695" frameX="-4" frameY="-12" frameWidth="398" frameHeight="707"/>
	<SubTexture name="hi0066" x="2797" y="705" width="316" height="695" frameX="-4" frameY="-12" frameWidth="398" frameHeight="707"/>
	<SubTexture name="hi0067" x="3113" y="705" width="316" height="695" frameX="-4" frameY="-12" frameWidth="398" frameHeight="707"/>
	<SubTexture name="hi0068" x="3429" y="705" width="316" height="695" frameX="-4" frameY="-12" frameWidth="398" frameHeight="707"/>
	<SubTexture name="hi0069" x="2165" y="705" width="316" height="695" frameX="-4" frameY="-12" frameWidth="398" frameHeight="707"/>
	<SubTexture name="hi0070" x="2165" y="705" width="316" height="695" frameX="-4" frameY="-12" frameWidth="398" frameHeight="707"/>
	<SubTexture name="hi0071" x="2481" y="705" width="316" height="695" frameX="-4" frameY="-12" frameWidth="398" frameHeight="707"/>
	<SubTexture name="hi0072" x="2797" y="705" width="316" height="695" frameX="-4" frameY="-12" frameWidth="398" frameHeight="707"/>
	<SubTexture name="hi0073" x="3745" y="705" width="316" height="695" frameX="-4" frameY="-12" frameWidth="398" frameHeight="707"/>
	<SubTexture name="hi0074" x="1849" y="705" width="316" height="695" frameX="-4" frameY="-12" frameWidth="398" frameHeight="707"/>
	<SubTexture name="hi0075" x="1849" y="705" width="316" height="695" frameX="-4" frameY="-12" frameWidth="398" frameHeight="707"/>
	<SubTexture name="hi0076" x="1849" y="705" width="316" height="695" frameX="-4" frameY="-12" frameWidth="398" frameHeight="707"/>
	<SubTexture name="hi0077" x="1849" y="705" width="316" height="695" frameX="-4" frameY="-12" frameWidth="398" frameHeight="707"/>
	<SubTexture name="hi0078" x="3745" y="705" width="316" height="695" frameX="-4" frameY="-12" frameWidth="398" frameHeight="707"/>
	<SubTexture name="hi0079" x="3745" y="705" width="316" height="695" frameX="-4" frameY="-12" frameWidth="398" frameHeight="707"/>
	<SubTexture name="hi0080" x="1849" y="705" width="316" height="695" frameX="-4" frameY="-12" frameWidth="398" frameHeight="707"/>
	<SubTexture name="hi0081" x="1849" y="705" width="316" height="695" frameX="-4" frameY="-12" frameWidth="398" frameHeight="707"/>
	<SubTexture name="hi0082" x="1849" y="705" width="316" height="695" frameX="-4" frameY="-12" frameWidth="398" frameHeight="707"/>
	<SubTexture name="hi0083" x="1849" y="705" width="316" height="695" frameX="-4" frameY="-12" frameWidth="398" frameHeight="707"/>
	<SubTexture name="hi0084" x="3745" y="705" width="316" height="695" frameX="-4" frameY="-12" frameWidth="398" frameHeight="707"/>
	<SubTexture name="hi0085" x="3745" y="705" width="316" height="695" frameX="-4" frameY="-12" frameWidth="398" frameHeight="707"/>
	<SubTexture name="hi0086" x="4061" y="705" width="319" height="690" frameX="-1" frameY="-17" frameWidth="398" frameHeight="707"/>
	<SubTexture name="hi0087" x="4061" y="705" width="319" height="690" frameX="-1" frameY="-17" frameWidth="398" frameHeight="707"/>
	<SubTexture name="hi0088" x="4061" y="705" width="319" height="690" frameX="-1" frameY="-17" frameWidth="398" frameHeight="707"/>
	<SubTexture name="hi0089" x="4061" y="705" width="319" height="690" frameX="-1" frameY="-17" frameWidth="398" frameHeight="707"/>
	<SubTexture name="hi0090" x="4380" y="705" width="317" height="697" frameX="-3" frameY="-10" frameWidth="398" frameHeight="707"/>
	<SubTexture name="hi0091" x="4380" y="705" width="317" height="697" frameX="-3" frameY="-10" frameWidth="398" frameHeight="707"/>
	<SubTexture name="hi0092" x="4697" y="705" width="320" height="697" frameX="0" frameY="-10" frameWidth="398" frameHeight="707"/>
	<SubTexture name="hi0093" x="4697" y="705" width="320" height="697" frameX="0" frameY="-10" frameWidth="398" frameHeight="707"/>
	<SubTexture name="hi0094" x="4697" y="705" width="320" height="697" frameX="0" frameY="-10" frameWidth="398" frameHeight="707"/>
	<SubTexture name="hi0095" x="4697" y="705" width="320" height="697" frameX="0" frameY="-10" frameWidth="398" frameHeight="707"/>
	<SubTexture name="hi0096" x="5017" y="705" width="320" height="697" frameX="0" frameY="-10" frameWidth="398" frameHeight="707"/>
	<SubTexture name="hi0097" x="5017" y="705" width="320" height="697" frameX="0" frameY="-10" frameWidth="398" frameHeight="707"/>
	<SubTexture name="hi0098" x="4697" y="705" width="320" height="697" frameX="0" frameY="-10" frameWidth="398" frameHeight="707"/>
	<SubTexture name="hi0099" x="4697" y="705" width="320" height="697" frameX="0" frameY="-10" frameWidth="398" frameHeight="707"/>
	<SubTexture name="hi0100" x="4697" y="705" width="320" height="697" frameX="0" frameY="-10" frameWidth="398" frameHeight="707"/>
	<SubTexture name="hi0101" x="4697" y="705" width="320" height="697" frameX="0" frameY="-10" frameWidth="398" frameHeight="707"/>
	<SubTexture name="hi0102" x="5017" y="705" width="320" height="697" frameX="0" frameY="-10" frameWidth="398" frameHeight="707"/>
	<SubTexture name="hi0103" x="5017" y="705" width="320" height="697" frameX="0" frameY="-10" frameWidth="398" frameHeight="707"/>
	<SubTexture name="hi0104" x="4697" y="705" width="320" height="697" frameX="0" frameY="-10" frameWidth="398" frameHeight="707"/>
	<SubTexture name="hi0105" x="4697" y="705" width="320" height="697" frameX="0" frameY="-10" frameWidth="398" frameHeight="707"/>
	<SubTexture name="hi0106" x="4697" y="705" width="320" height="697" frameX="0" frameY="-10" frameWidth="398" frameHeight="707"/>
	<SubTexture name="hi0107" x="4697" y="705" width="320" height="697" frameX="0" frameY="-10" frameWidth="398" frameHeight="707"/>
	<SubTexture name="hi0108" x="5017" y="705" width="320" height="697" frameX="0" frameY="-10" frameWidth="398" frameHeight="707"/>
	<SubTexture name="hi0109" x="5017" y="705" width="320" height="697" frameX="0" frameY="-10" frameWidth="398" frameHeight="707"/>
	<SubTexture name="hi0110" x="4697" y="705" width="320" height="697" frameX="0" frameY="-10" frameWidth="398" frameHeight="707"/>
	<SubTexture name="hi0111" x="4697" y="705" width="320" height="697" frameX="0" frameY="-10" frameWidth="398" frameHeight="707"/>
	<SubTexture name="hi0112" x="4697" y="705" width="320" height="697" frameX="0" frameY="-10" frameWidth="398" frameHeight="707"/>
	<SubTexture name="hi0113" x="4697" y="705" width="320" height="697" frameX="0" frameY="-10" frameWidth="398" frameHeight="707"/>
	<SubTexture name="hi0114" x="5017" y="705" width="320" height="697" frameX="0" frameY="-10" frameWidth="398" frameHeight="707"/>
	<SubTexture name="hi0115" x="5017" y="705" width="320" height="697" frameX="0" frameY="-10" frameWidth="398" frameHeight="707"/>
	<SubTexture name="hi0116" x="4697" y="705" width="320" height="697" frameX="0" frameY="-10" frameWidth="398" frameHeight="707"/>
	<SubTexture name="hi0117" x="5337" y="705" width="314" height="707" frameX="-6" frameY="0" frameWidth="398" frameHeight="707"/>
	<SubTexture name="hi0118" x="5337" y="705" width="314" height="707" frameX="-6" frameY="0" frameWidth="398" frameHeight="707"/>
	<SubTexture name="hi0119" x="5651" y="705" width="317" height="692" frameX="-3" frameY="-15" frameWidth="398" frameHeight="707"/>
	<SubTexture name="hi0120" x="5968" y="705" width="317" height="692" frameX="-3" frameY="-15" frameWidth="398" frameHeight="707"/>
	<SubTexture name="hi0121" x="6285" y="705" width="314" height="698" frameX="-6" frameY="-9" frameWidth="398" frameHeight="707"/>
	<SubTexture name="hi0122" x="6599" y="705" width="314" height="698" frameX="-6" frameY="-9" frameWidth="398" frameHeight="707"/>
	<SubTexture name="hi0123" x="6913" y="705" width="314" height="698" frameX="-6" frameY="-9" frameWidth="398" frameHeight="707"/>
	<SubTexture name="hi0124" x="7227" y="705" width="314" height="698" frameX="-6" frameY="-9" frameWidth="398" frameHeight="707"/>
	<SubTexture name="hi0125" x="7227" y="705" width="314" height="698" frameX="-6" frameY="-9" frameWidth="398" frameHeight="707"/>
	<SubTexture name="hi0126" x="7541" y="705" width="314" height="698" frameX="-6" frameY="-9" frameWidth="398" frameHeight="707"/>
	<SubTexture name="hi0127" x="7541" y="705" width="314" height="698" frameX="-6" frameY="-9" frameWidth="398" frameHeight="707"/>
	<SubTexture name="hi0128" x="7227" y="705" width="314" height="698" frameX="-6" frameY="-9" frameWidth="398" frameHeight="707"/>
	<SubTexture name="hi0129" x="7227" y="705" width="314" height="698" frameX="-6" frameY="-9" frameWidth="398" frameHeight="707"/>
	<SubTexture name="hi0130" x="7227" y="705" width="314" height="698" frameX="-6" frameY="-9" frameWidth="398" frameHeight="707"/>
	<SubTexture name="hi0131" x="7227" y="705" width="314" height="698" frameX="-6" frameY="-9" frameWidth="398" frameHeight="707"/>
	<SubTexture name="hi0132" x="7541" y="705" width="314" height="698" frameX="-6" frameY="-9" frameWidth="398" frameHeight="707"/>
	<SubTexture name="hi0133" x="7541" y="705" width="314" height="698" frameX="-6" frameY="-9" frameWidth="398" frameHeight="707"/>
	<SubTexture name="hi0134" x="7227" y="705" width="314" height="698" frameX="-6" frameY="-9" frameWidth="398" frameHeight="707"/>
	<SubTexture name="hi0135" x="7855" y="705" width="314" height="698" frameX="-6" frameY="-9" frameWidth="398" frameHeight="707"/>
	<SubTexture name="hi0136" x="7855" y="705" width="314" height="698" frameX="-6" frameY="-9" frameWidth="398" frameHeight="707"/>
	<SubTexture name="hi0137" x="6599" y="705" width="314" height="698" frameX="-6" frameY="-9" frameWidth="398" frameHeight="707"/>
	<SubTexture name="hi0138" x="6285" y="705" width="314" height="698" frameX="-6" frameY="-9" frameWidth="398" frameHeight="707"/>
	<SubTexture name="hi0139" x="0" y="1412" width="314" height="698" frameX="-6" frameY="-9" frameWidth="398" frameHeight="707"/>
	<SubTexture name="hi0140" x="6913" y="705" width="314" height="698" frameX="-6" frameY="-9" frameWidth="398" frameHeight="707"/>
	<SubTexture name="hi0141" x="6913" y="705" width="314" height="698" frameX="-6" frameY="-9" frameWidth="398" frameHeight="707"/>
	<SubTexture name="hi0142" x="6913" y="705" width="314" height="698" frameX="-6" frameY="-9" frameWidth="398" frameHeight="707"/>
	<SubTexture name="hi0143" x="314" y="1412" width="314" height="698" frameX="-6" frameY="-9" frameWidth="398" frameHeight="707"/>
	<SubTexture name="hi0144" x="628" y="1412" width="314" height="698" frameX="-6" frameY="-9" frameWidth="398" frameHeight="707"/>
	<SubTexture name="hi0145" x="6285" y="705" width="314" height="698" frameX="-6" frameY="-9" frameWidth="398" frameHeight="707"/>
	<SubTexture name="hi0146" x="6599" y="705" width="314" height="698" frameX="-6" frameY="-9" frameWidth="398" frameHeight="707"/>
	<SubTexture name="hi0147" x="6913" y="705" width="314" height="698" frameX="-6" frameY="-9" frameWidth="398" frameHeight="707"/>
	<SubTexture name="hi0148" x="6913" y="705" width="314" height="698" frameX="-6" frameY="-9" frameWidth="398" frameHeight="707"/>
	<SubTexture name="hi0149" x="7855" y="705" width="314" height="698" frameX="-6" frameY="-9" frameWidth="398" frameHeight="707"/>
	<SubTexture name="hi0150" x="942" y="1412" width="314" height="698" frameX="-6" frameY="-9" frameWidth="398" frameHeight="707"/>
	<SubTexture name="hi0151" x="942" y="1412" width="314" height="698" frameX="-6" frameY="-9" frameWidth="398" frameHeight="707"/>
	<SubTexture name="hi0152" x="6599" y="705" width="314" height="698" frameX="-6" frameY="-9" frameWidth="398" frameHeight="707"/>
	<SubTexture name="hi0153" x="6599" y="705" width="314" height="698" frameX="-6" frameY="-9" frameWidth="398" frameHeight="707"/>
	<SubTexture name="hi0154" x="6913" y="705" width="314" height="698" frameX="-6" frameY="-9" frameWidth="398" frameHeight="707"/>
	<SubTexture name="hi0155" x="6913" y="705" width="314" height="698" frameX="-6" frameY="-9" frameWidth="398" frameHeight="707"/>
	<SubTexture name="hi0156" x="7541" y="705" width="314" height="698" frameX="-6" frameY="-9" frameWidth="398" frameHeight="707"/>
	<SubTexture name="hi0157" x="7541" y="705" width="314" height="698" frameX="-6" frameY="-9" frameWidth="398" frameHeight="707"/>
	<SubTexture name="hi0158" x="7227" y="705" width="314" height="698" frameX="-6" frameY="-9" frameWidth="398" frameHeight="707"/>
	<SubTexture name="hi0159" x="7227" y="705" width="314" height="698" frameX="-6" frameY="-9" frameWidth="398" frameHeight="707"/>
	<SubTexture name="hi0160" x="7227" y="705" width="314" height="698" frameX="-6" frameY="-9" frameWidth="398" frameHeight="707"/>
	<SubTexture name="hi0161" x="7227" y="705" width="314" height="698" frameX="-6" frameY="-9" frameWidth="398" frameHeight="707"/>
	<SubTexture name="hi0162" x="1256" y="1412" width="320" height="690" frameX="0" frameY="-17" frameWidth="398" frameHeight="707"/>
	<SubTexture name="hi0163" x="1576" y="1412" width="312" height="690" frameX="0" frameY="-17" frameWidth="398" frameHeight="707"/>
	<SubTexture name="hi0164" x="1888" y="1412" width="309" height="701" frameX="-3" frameY="-6" frameWidth="398" frameHeight="707"/>
	<SubTexture name="hi0165" x="2197" y="1412" width="309" height="701" frameX="-3" frameY="-6" frameWidth="398" frameHeight="707"/>
	<SubTexture name="hi0166" x="2506" y="1412" width="311" height="691" frameX="-1" frameY="-16" frameWidth="398" frameHeight="707"/>
	<SubTexture name="hi0167" x="2817" y="1412" width="310" height="691" frameX="-1" frameY="-16" frameWidth="398" frameHeight="707"/>
	<SubTexture name="hi0168" x="3127" y="1412" width="310" height="691" frameX="-1" frameY="-16" frameWidth="398" frameHeight="707"/>
	<SubTexture name="hi0169" x="3127" y="1412" width="310" height="691" frameX="-1" frameY="-16" frameWidth="398" frameHeight="707"/>
	<SubTexture name="hi0170" x="3437" y="1412" width="310" height="691" frameX="-1" frameY="-16" frameWidth="398" frameHeight="707"/>
	<SubTexture name="hi0171" x="3437" y="1412" width="310" height="691" frameX="-1" frameY="-16" frameWidth="398" frameHeight="707"/>
	<SubTexture name="hi0172" x="3747" y="1412" width="310" height="691" frameX="-1" frameY="-16" frameWidth="398" frameHeight="707"/>
	<SubTexture name="hi0173" x="3747" y="1412" width="310" height="691" frameX="-1" frameY="-16" frameWidth="398" frameHeight="707"/>
	<SubTexture name="hi0174" x="4057" y="1412" width="310" height="691" frameX="-1" frameY="-16" frameWidth="398" frameHeight="707"/>
	<SubTexture name="hi0175" x="4057" y="1412" width="310" height="691" frameX="-1" frameY="-16" frameWidth="398" frameHeight="707"/>
	<SubTexture name="hi0176" x="3437" y="1412" width="310" height="691" frameX="-1" frameY="-16" frameWidth="398" frameHeight="707"/>
	<SubTexture name="hi0177" x="3437" y="1412" width="310" height="691" frameX="-1" frameY="-16" frameWidth="398" frameHeight="707"/>
	<SubTexture name="hi0178" x="4367" y="1412" width="310" height="691" frameX="-1" frameY="-16" frameWidth="398" frameHeight="707"/>
	<SubTexture name="hi0179" x="4367" y="1412" width="310" height="691" frameX="-1" frameY="-16" frameWidth="398" frameHeight="707"/>
	<SubTexture name="hi0180" x="4677" y="1412" width="310" height="691" frameX="-1" frameY="-16" frameWidth="398" frameHeight="707"/>
	<SubTexture name="hi0181" x="4677" y="1412" width="310" height="691" frameX="-1" frameY="-16" frameWidth="398" frameHeight="707"/>
	<SubTexture name="hi0182" x="2817" y="1412" width="310" height="691" frameX="-1" frameY="-16" frameWidth="398" frameHeight="707"/>
	<SubTexture name="hi0183" x="2817" y="1412" width="310" height="691" frameX="-1" frameY="-16" frameWidth="398" frameHeight="707"/>
	<SubTexture name="hi0184" x="2817" y="1412" width="310" height="691" frameX="-1" frameY="-16" frameWidth="398" frameHeight="707"/>
	<SubTexture name="hi0185" x="2817" y="1412" width="310" height="691" frameX="-1" frameY="-16" frameWidth="398" frameHeight="707"/>
	<SubTexture name="hi0186" x="4057" y="1412" width="310" height="691" frameX="-1" frameY="-16" frameWidth="398" frameHeight="707"/>
	<SubTexture name="hi0187" x="4057" y="1412" width="310" height="691" frameX="-1" frameY="-16" frameWidth="398" frameHeight="707"/>
	<SubTexture name="hi0188" x="2817" y="1412" width="310" height="691" frameX="-1" frameY="-16" frameWidth="398" frameHeight="707"/>
	<SubTexture name="hi0189" x="2817" y="1412" width="310" height="691" frameX="-1" frameY="-16" frameWidth="398" frameHeight="707"/>
	<SubTexture name="hi0190" x="2817" y="1412" width="310" height="691" frameX="-1" frameY="-16" frameWidth="398" frameHeight="707"/>
	<SubTexture name="hi0191" x="2817" y="1412" width="310" height="691" frameX="-1" frameY="-16" frameWidth="398" frameHeight="707"/>
	<SubTexture name="hi0192" x="4987" y="1412" width="310" height="691" frameX="-1" frameY="-16" frameWidth="398" frameHeight="707"/>
	<SubTexture name="hi0193" x="4987" y="1412" width="310" height="691" frameX="-1" frameY="-16" frameWidth="398" frameHeight="707"/>
	<SubTexture name="hi0194" x="3437" y="1412" width="310" height="691" frameX="-1" frameY="-16" frameWidth="398" frameHeight="707"/>
	<SubTexture name="hi0195" x="3437" y="1412" width="310" height="691" frameX="-1" frameY="-16" frameWidth="398" frameHeight="707"/>
	<SubTexture name="hi0196" x="3747" y="1412" width="310" height="691" frameX="-1" frameY="-16" frameWidth="398" frameHeight="707"/>
	<SubTexture name="hi0197" x="3747" y="1412" width="310" height="691" frameX="-1" frameY="-16" frameWidth="398" frameHeight="707"/>
	<SubTexture name="hi0198" x="4057" y="1412" width="310" height="691" frameX="-1" frameY="-16" frameWidth="398" frameHeight="707"/>
	<SubTexture name="hi0199" x="4057" y="1412" width="310" height="691" frameX="-1" frameY="-16" frameWidth="398" frameHeight="707"/>
	<SubTexture name="hi0200" x="3437" y="1412" width="310" height="691" frameX="-1" frameY="-16" frameWidth="398" frameHeight="707"/>
	<SubTexture name="hi0201" x="3437" y="1412" width="310" height="691" frameX="-1" frameY="-16" frameWidth="398" frameHeight="707"/>
	<SubTexture name="hi0202" x="4367" y="1412" width="310" height="691" frameX="-1" frameY="-16" frameWidth="398" frameHeight="707"/>
	<SubTexture name="hi0203" x="4367" y="1412" width="310" height="691" frameX="-1" frameY="-16" frameWidth="398" frameHeight="707"/>
	<SubTexture name="hi0204" x="4677" y="1412" width="310" height="691" frameX="-1" frameY="-16" frameWidth="398" frameHeight="707"/>
	<SubTexture name="hi0205" x="4677" y="1412" width="310" height="691" frameX="-1" frameY="-16" frameWidth="398" frameHeight="707"/>
	<SubTexture name="hi0206" x="3747" y="1412" width="310" height="691" frameX="-1" frameY="-16" frameWidth="398" frameHeight="707"/>
	<SubTexture name="hi0207" x="3747" y="1412" width="310" height="691" frameX="-1" frameY="-16" frameWidth="398" frameHeight="707"/>
	<SubTexture name="hi0208" x="2817" y="1412" width="310" height="691" frameX="-1" frameY="-16" frameWidth="398" frameHeight="707"/>
	<SubTexture name="hi0209" x="2817" y="1412" width="310" height="691" frameX="-1" frameY="-16" frameWidth="398" frameHeight="707"/>
	<SubTexture name="hi0210" x="4057" y="1412" width="310" height="691" frameX="-1" frameY="-16" frameWidth="398" frameHeight="707"/>
	<SubTexture name="hi0211" x="4057" y="1412" width="310" height="691" frameX="-1" frameY="-16" frameWidth="398" frameHeight="707"/>
	<SubTexture name="hi0212" x="5297" y="1412" width="310" height="691" frameX="-1" frameY="-16" frameWidth="398" frameHeight="707"/>
	<SubTexture name="hi0213" x="5297" y="1412" width="310" height="691" frameX="-1" frameY="-16" frameWidth="398" frameHeight="707"/>
	<SubTexture name="hi0214" x="5297" y="1412" width="310" height="691" frameX="-1" frameY="-16" frameWidth="398" frameHeight="707"/>
	<SubTexture name="hi0215" x="5297" y="1412" width="310" height="691" frameX="-1" frameY="-16" frameWidth="398" frameHeight="707"/>
	<SubTexture name="hi0216" x="5607" y="1412" width="310" height="691" frameX="-1" frameY="-16" frameWidth="398" frameHeight="707"/>
	<SubTexture name="hi0217" x="5607" y="1412" width="310" height="691" frameX="-1" frameY="-16" frameWidth="398" frameHeight="707"/>
	<SubTexture name="hi0218" x="3437" y="1412" width="310" height="691" frameX="-1" frameY="-16" frameWidth="398" frameHeight="707"/>
	<SubTexture name="hi0219" x="3437" y="1412" width="310" height="691" frameX="-1" frameY="-16" frameWidth="398" frameHeight="707"/>
	<SubTexture name="hi0220" x="3747" y="1412" width="310" height="691" frameX="-1" frameY="-16" frameWidth="398" frameHeight="707"/>
	<SubTexture name="hi0221" x="3747" y="1412" width="310" height="691" frameX="-1" frameY="-16" frameWidth="398" frameHeight="707"/>
	<SubTexture name="hi0222" x="4987" y="1412" width="310" height="691" frameX="-1" frameY="-16" frameWidth="398" frameHeight="707"/>
	<SubTexture name="hi0223" x="4987" y="1412" width="310" height="691" frameX="-1" frameY="-16" frameWidth="398" frameHeight="707"/>
	<SubTexture name="hi0224" x="3437" y="1412" width="310" height="691" frameX="-1" frameY="-16" frameWidth="398" frameHeight="707"/>
	<SubTexture name="hi0225" x="3437" y="1412" width="310" height="691" frameX="-1" frameY="-16" frameWidth="398" frameHeight="707"/>
	<SubTexture name="hi0226" x="3747" y="1412" width="310" height="691" frameX="-1" frameY="-16" frameWidth="398" frameHeight="707"/>
	<SubTexture name="hi0227" x="3747" y="1412" width="310" height="691" frameX="-1" frameY="-16" frameWidth="398" frameHeight="707"/>
	<SubTexture name="hi0228" x="4057" y="1412" width="310" height="691" frameX="-1" frameY="-16" frameWidth="398" frameHeight="707"/>
	<SubTexture name="hi0229" x="4057" y="1412" width="310" height="691" frameX="-1" frameY="-16" frameWidth="398" frameHeight="707"/>
	<SubTexture name="hi0230" x="5297" y="1412" width="310" height="691" frameX="-1" frameY="-16" frameWidth="398" frameHeight="707"/>
	<SubTexture name="hi0231" x="5297" y="1412" width="310" height="691" frameX="-1" frameY="-16" frameWidth="398" frameHeight="707"/>
	<SubTexture name="hi0232" x="3437" y="1412" width="310" height="691" frameX="-1" frameY="-16" frameWidth="398" frameHeight="707"/>
	<SubTexture name="hi0233" x="3437" y="1412" width="310" height="691" frameX="-1" frameY="-16" frameWidth="398" frameHeight="707"/>
	<SubTexture name="hi0234" x="5917" y="1412" width="310" height="691" frameX="-1" frameY="-16" frameWidth="398" frameHeight="707"/>
	<SubTexture name="hi0235" x="5917" y="1412" width="310" height="691" frameX="-1" frameY="-16" frameWidth="398" frameHeight="707"/>
	<SubTexture name="hi0236" x="3747" y="1412" width="310" height="691" frameX="-1" frameY="-16" frameWidth="398" frameHeight="707"/>
	<SubTexture name="hi0237" x="3747" y="1412" width="310" height="691" frameX="-1" frameY="-16" frameWidth="398" frameHeight="707"/>
	<SubTexture name="hi0238" x="2817" y="1412" width="310" height="691" frameX="-1" frameY="-16" frameWidth="398" frameHeight="707"/>
	<SubTexture name="hi0239" x="2817" y="1412" width="310" height="691" frameX="-1" frameY="-16" frameWidth="398" frameHeight="707"/>
	<SubTexture name="hi0240" x="5607" y="1412" width="310" height="691" frameX="-1" frameY="-16" frameWidth="398" frameHeight="707"/>
	<SubTexture name="hi0241" x="5607" y="1412" width="310" height="691" frameX="-1" frameY="-16" frameWidth="398" frameHeight="707"/>
	<SubTexture name="hi0242" x="5297" y="1412" width="310" height="691" frameX="-1" frameY="-16" frameWidth="398" frameHeight="707"/>
	<SubTexture name="hi0243" x="5297" y="1412" width="310" height="691" frameX="-1" frameY="-16" frameWidth="398" frameHeight="707"/>
	<SubTexture name="hi0244" x="5297" y="1412" width="310" height="691" frameX="-1" frameY="-16" frameWidth="398" frameHeight="707"/>
	<SubTexture name="hi0245" x="5297" y="1412" width="310" height="691" frameX="-1" frameY="-16" frameWidth="398" frameHeight="707"/>
	<SubTexture name="hi0246" x="5607" y="1412" width="310" height="691" frameX="-1" frameY="-16" frameWidth="398" frameHeight="707"/>
	<SubTexture name="hi0247" x="5917" y="1412" width="310" height="691" frameX="-1" frameY="-16" frameWidth="398" frameHeight="707"/>
	<SubTexture name="hi0248" x="3437" y="1412" width="310" height="691" frameX="-1" frameY="-16" frameWidth="398" frameHeight="707"/>
	<SubTexture name="hi0249" x="3747" y="1412" width="310" height="691" frameX="-1" frameY="-16" frameWidth="398" frameHeight="707"/>
	<SubTexture name="hi0250" x="3747" y="1412" width="310" height="691" frameX="-1" frameY="-16" frameWidth="398" frameHeight="707"/>
	<SubTexture name="hi0251" x="2817" y="1412" width="310" height="691" frameX="-1" frameY="-16" frameWidth="398" frameHeight="707"/>
	<SubTexture name="hi0252" x="4057" y="1412" width="310" height="691" frameX="-1" frameY="-16" frameWidth="398" frameHeight="707"/>
	<SubTexture name="hi0253" x="5607" y="1412" width="310" height="691" frameX="-1" frameY="-16" frameWidth="398" frameHeight="707"/>
	<SubTexture name="hi0254" x="5297" y="1412" width="310" height="691" frameX="-1" frameY="-16" frameWidth="398" frameHeight="707"/>
	<SubTexture name="hi0255" x="5297" y="1412" width="310" height="691" frameX="-1" frameY="-16" frameWidth="398" frameHeight="707"/>
	<SubTexture name="hi0256" x="5297" y="1412" width="310" height="691" frameX="-1" frameY="-16" frameWidth="398" frameHeight="707"/>
	<SubTexture name="hi0257" x="5297" y="1412" width="310" height="691" frameX="-1" frameY="-16" frameWidth="398" frameHeight="707"/>
	<SubTexture name="hi0258" x="5607" y="1412" width="310" height="691" frameX="-1" frameY="-16" frameWidth="398" frameHeight="707"/>
	<SubTexture name="hi0259" x="5607" y="1412" width="310" height="691" frameX="-1" frameY="-16" frameWidth="398" frameHeight="707"/>
	<SubTexture name="hi0260" x="5297" y="1412" width="310" height="691" frameX="-1" frameY="-16" frameWidth="398" frameHeight="707"/>
	<SubTexture name="hi0261" x="5297" y="1412" width="310" height="691" frameX="-1" frameY="-16" frameWidth="398" frameHeight="707"/>
	<SubTexture name="hi0262" x="5297" y="1412" width="310" height="691" frameX="-1" frameY="-16" frameWidth="398" frameHeight="707"/>
	<SubTexture name="hi0263" x="5297" y="1412" width="310" height="691" frameX="-1" frameY="-16" frameWidth="398" frameHeight="707"/>
	<SubTexture name="hi0264" x="5607" y="1412" width="310" height="691" frameX="-1" frameY="-16" frameWidth="398" frameHeight="707"/>
	<SubTexture name="hi0265" x="5607" y="1412" width="310" height="691" frameX="-1" frameY="-16" frameWidth="398" frameHeight="707"/>
	<SubTexture name="hi0266" x="5297" y="1412" width="310" height="691" frameX="-1" frameY="-16" frameWidth="398" frameHeight="707"/>
	<SubTexture name="hi0267" x="5297" y="1412" width="310" height="691" frameX="-1" frameY="-16" frameWidth="398" frameHeight="707"/>
	<SubTexture name="hi0268" x="5297" y="1412" width="310" height="691" frameX="-1" frameY="-16" frameWidth="398" frameHeight="707"/>
	<SubTexture name="hi0269" x="5297" y="1412" width="310" height="691" frameX="-1" frameY="-16" frameWidth="398" frameHeight="707"/>
	<SubTexture name="hi0270" x="5607" y="1412" width="310" height="691" frameX="-1" frameY="-16" frameWidth="398" frameHeight="707"/>
	<SubTexture name="hi0271" x="5607" y="1412" width="310" height="691" frameX="-1" frameY="-16" frameWidth="398" frameHeight="707"/>
	<SubTexture name="hi0272" x="5297" y="1412" width="310" height="691" frameX="-1" frameY="-16" frameWidth="398" frameHeight="707"/>
	<SubTexture name="hi0273" x="5297" y="1412" width="310" height="691" frameX="-1" frameY="-16" frameWidth="398" frameHeight="707"/>
	<SubTexture name="hi0274" x="5297" y="1412" width="310" height="691" frameX="-1" frameY="-16" frameWidth="398" frameHeight="707"/>
	<SubTexture name="hi0275" x="5297" y="1412" width="310" height="691" frameX="-1" frameY="-16" frameWidth="398" frameHeight="707"/>
	<SubTexture name="hi0276" x="5607" y="1412" width="310" height="691" frameX="-1" frameY="-16" frameWidth="398" frameHeight="707"/>
	<SubTexture name="hi0277" x="5607" y="1412" width="310" height="691" frameX="-1" frameY="-16" frameWidth="398" frameHeight="707"/>
	<SubTexture name="hi0278" x="5297" y="1412" width="310" height="691" frameX="-1" frameY="-16" frameWidth="398" frameHeight="707"/>
	<SubTexture name="hi0279" x="5297" y="1412" width="310" height="691" frameX="-1" frameY="-16" frameWidth="398" frameHeight="707"/>
	<SubTexture name="hi0280" x="5297" y="1412" width="310" height="691" frameX="-1" frameY="-16" frameWidth="398" frameHeight="707"/>
	<SubTexture name="hi0281" x="5297" y="1412" width="310" height="691" frameX="-1" frameY="-16" frameWidth="398" frameHeight="707"/>
	<SubTexture name="hi0282" x="5607" y="1412" width="310" height="691" frameX="-1" frameY="-16" frameWidth="398" frameHeight="707"/>
	<SubTexture name="hi0283" x="5607" y="1412" width="310" height="691" frameX="-1" frameY="-16" frameWidth="398" frameHeight="707"/>
	<SubTexture name="reggie idle0000" x="6227" y="1412" width="275" height="697"/>
	<SubTexture name="reggie idle0001" x="6227" y="1412" width="275" height="697"/>
	<SubTexture name="reggie idle0002" x="6502" y="1412" width="275" height="696" frameX="0" frameY="0" frameWidth="275" frameHeight="697"/>
	<SubTexture name="reggie idle0003" x="6502" y="1412" width="275" height="696" frameX="0" frameY="0" frameWidth="275" frameHeight="697"/>
	<SubTexture name="reggie idle0004" x="6502" y="1412" width="275" height="696" frameX="0" frameY="0" frameWidth="275" frameHeight="697"/>
	<SubTexture name="reggie idle0005" x="6502" y="1412" width="275" height="696" frameX="0" frameY="0" frameWidth="275" frameHeight="697"/>
	<SubTexture name="reggie idle0006" x="6227" y="1412" width="275" height="697"/>
	<SubTexture name="reggie idle0007" x="6227" y="1412" width="275" height="697"/>
	<SubTexture name="reggie idle0008" x="6502" y="1412" width="275" height="696" frameX="0" frameY="0" frameWidth="275" frameHeight="697"/>
	<SubTexture name="reggie idle0009" x="6502" y="1412" width="275" height="696" frameX="0" frameY="0" frameWidth="275" frameHeight="697"/>
	<SubTexture name="reggie idle0010" x="6502" y="1412" width="275" height="696" frameX="0" frameY="0" frameWidth="275" frameHeight="697"/>
	<SubTexture name="reggie idle0011" x="6502" y="1412" width="275" height="696" frameX="0" frameY="0" frameWidth="275" frameHeight="697"/>
	<SubTexture name="reggie idle0012" x="6227" y="1412" width="275" height="697"/>
	<SubTexture name="reggie idle0013" x="6227" y="1412" width="275" height="697"/>
	<SubTexture name="reggie idle0014" x="6502" y="1412" width="275" height="696" frameX="0" frameY="0" frameWidth="275" frameHeight="697"/>
</TextureAtlas>
